{
  "updated_at": "2026-05-13T01:23:13+00:00",
  "updated_at_ct": "2026-05-12 20:23 CT",
  "source_updated_at": "Wed, 13 May 2026 00:02:31 +0000",
  "provider": "https://www.exchangerate-api.com",
  "fetched_live": true,
  "is_complete_update": true,
  "last_complete_update": "2026-05-12 20:23 CT",
  "last_partial_update": "",
  "missing_live_currencies": [],
  "base_currency": "USD",
  "currency_to_usd_rate": {
    "USD": 1,
    "USDC": 1,
    "AED": 0.27229407760381213,
    "AUD": 0.7232728966500893,
    "BRL": 0.2042655967507063,
    "CAD": 0.7299936125558901,
    "CHF": 1.280593375746586,
    "CNY": 0.14687080729742294,
    "DKK": 0.15727363016634047,
    "EUR": 1.1738728766107003,
    "GBP": 1.3535371309073436,
    "ILS": 0.34365713739790377,
    "INR": 0.010452311444012121,
    "JPY": 0.006345758446826377,
    "KRW": 0.000671049596236202,
    "RUB": 0.013538102183077192,
    "SEK": 0.10760968332191953,
    "SGD": 0.78610048565288,
    "TWD": 0.03169251365464028,
    "ZAR": 0.06053927294633684
  },
  "nation_rates": [
    {
      "nation": "Australia",
      "currency": "AUD",
      "usd_rate": 0.7232728966500893,
      "rate_source": "live"
    },
    {
      "nation": "Brazil",
      "currency": "BRL",
      "usd_rate": 0.2042655967507063,
      "rate_source": "live"
    },
    {
      "nation": "Britain",
      "currency": "GBP",
      "usd_rate": 1.3535371309073436,
      "rate_source": "live"
    },
    {
      "nation": "Canada",
      "currency": "CAD",
      "usd_rate": 0.7299936125558901,
      "rate_source": "live"
    },
    {
      "nation": "China",
      "currency": "CNY",
      "usd_rate": 0.14687080729742294,
      "rate_source": "live"
    },
    {
      "nation": "Denmark",
      "currency": "DKK",
      "usd_rate": 0.15727363016634047,
      "rate_source": "live"
    },
    {
      "nation": "Dubai",
      "currency": "AED",
      "usd_rate": 0.27229407760381213,
      "rate_source": "live"
    },
    {
      "nation": "Finland",
      "currency": "EUR",
      "usd_rate": 1.1738728766107003,
      "rate_source": "live"
    },
    {
      "nation": "France",
      "currency": "EUR",
      "usd_rate": 1.1738728766107003,
      "rate_source": "live"
    },
    {
      "nation": "Germany",
      "currency": "EUR",
      "usd_rate": 1.1738728766107003,
      "rate_source": "live"
    },
    {
      "nation": "India",
      "currency": "INR",
      "usd_rate": 0.010452311444012121,
      "rate_source": "live"
    },
    {
      "nation": "Ireland",
      "currency": "EUR",
      "usd_rate": 1.1738728766107003,
      "rate_source": "live"
    },
    {
      "nation": "Israel",
      "currency": "ILS",
      "usd_rate": 0.34365713739790377,
      "rate_source": "live"
    },
    {
      "nation": "Japan",
      "currency": "JPY",
      "usd_rate": 0.006345758446826377,
      "rate_source": "live"
    },
    {
      "nation": "Luxembourg",
      "currency": "EUR",
      "usd_rate": 1.1738728766107003,
      "rate_source": "live"
    },
    {
      "nation": "Netherlands",
      "currency": "EUR",
      "usd_rate": 1.1738728766107003,
      "rate_source": "live"
    },
    {
      "nation": "Portugal",
      "currency": "EUR",
      "usd_rate": 1.1738728766107003,
      "rate_source": "live"
    },
    {
      "nation": "Russia",
      "currency": "RUB",
      "usd_rate": 0.013538102183077192,
      "rate_source": "live"
    },
    {
      "nation": "Singapore",
      "currency": "SGD",
      "usd_rate": 0.78610048565288,
      "rate_source": "live"
    },
    {
      "nation": "South Korea",
      "currency": "KRW",
      "usd_rate": 0.000671049596236202,
      "rate_source": "live"
    },
    {
      "nation": "Spain",
      "currency": "EUR",
      "usd_rate": 1.1738728766107003,
      "rate_source": "live"
    },
    {
      "nation": "Switzerland",
      "currency": "CHF",
      "usd_rate": 1.280593375746586,
      "rate_source": "live"
    },
    {
      "nation": "Taiwan",
      "currency": "TWD",
      "usd_rate": 0.03169251365464028,
      "rate_source": "live"
    },
    {
      "nation": "UAE",
      "currency": "AED",
      "usd_rate": 0.27229407760381213,
      "rate_source": "live"
    },
    {
      "nation": "USA",
      "currency": "USD",
      "usd_rate": 1,
      "rate_source": "fixed"
    }
  ]
}
